LICENSE
MANIFEST.in
README.md
setup.py
PyCoolPlot.egg-info/PKG-INFO
PyCoolPlot.egg-info/SOURCES.txt
PyCoolPlot.egg-info/dependency_links.txt
PyCoolPlot.egg-info/requires.txt
PyCoolPlot.egg-info/top_level.txt
pycoolplot/VERSION
pycoolplot/__init__.py
pycoolplot/pycoolplot.py