Metadata-Version: 2.1
Name: PyCoolPlot
Version: 0.1.0
Summary: A cool plotting module in Python
Home-page: https://github.com/AtsushiSakai/PyCoolPlot
Author: Atsushi Sakai
Author-email: asakai.amsl@gmail.com
Maintainer: Atsushi Sakai
Maintainer-email: asakai.amsl@gmail.com
License: MIT
Keywords: python plot matplotlib
Platform: UNKNOWN
Classifier: Programming Language :: Python :: 3
Classifier: License :: OSI Approved :: MIT License
Classifier: Topic :: Scientific/Engineering :: Visualization
Requires-Python: >3.6.0
License-File: LICENSE
